setup.py
pump/__init__.py
pump/adapters.py
pump.egg-info/PKG-INFO
pump.egg-info/SOURCES.txt
pump.egg-info/dependency_links.txt
pump.egg-info/requires.txt
pump.egg-info/top_level.txt
pump/middleware/__init__.py
pump/middleware/content_type.py
pump/middleware/cookies.py
pump/middleware/file.py
pump/middleware/nested_params.py
pump/middleware/params.py
pump/middleware/session.py
pump/middleware/static.py
pump/util/__init__.py
pump/util/codec.py
pump/util/response.py
pump/util/wsgi.py