Metadata-Version: 1.0
Name: pump
Version: 0.1.2
Summary: A web application library.
Home-page: UNKNOWN
Author: Adeel Ahmad Khan
Author-email: adeel@adeel.ru
License: MIT
Platform: UNKNOWN
Classifier: Topic :: Internet :: WWW/HTTP :: WSGI
Classifier: Development Status :: 3 - Alpha
Classifier: License :: OSI Approved :: MIT License
